CHANGElog.txt
LICENSE.txt
MANIFEST.in
README.txt
setup.py
Cls_Evaluation.egg-info/PKG-INFO
Cls_Evaluation.egg-info/SOURCES.txt
Cls_Evaluation.egg-info/dependency_links.txt
Cls_Evaluation.egg-info/top_level.txt
Cls_evaluation/__init__.py