Metadata-Version: 2.1
Name: Cls-Evaluation
Version: 0.0.1
Summary: Basic metrics for evaluating classification results
Home-page: UNKNOWN
Author: Swayanshu Shanti Pragnya
Author-email: swayanshu1997@gmail.com
License: MIT
Keywords: summary,F1 score,accuracy,confusion matrix,FDR
Platform: UNKNOWN
Classifier: Development Status :: 5 - Production/Stable
Classifier: Intended Audience :: Education
Classifier: Operating System :: Microsoft :: Windows :: Windows 10
Classifier: License :: OSI Approved :: MIT License
Classifier: Programming Language :: Python :: 3
License-File: LICENSE.txt
